{
    "pitanje_1" : "Koja reka je najduža na svetu: ",
    "odgovori_1" : ["Amazon", "Nil", "Dunav", "Gang"],
    "pitanje_2" : "Gde se nalazi planina Kilimandzaro: ",
    "odgovori_2" : ["Tanzanija", "Zambija", "Kenija", "Somalija"],
    "pitanje_3" : "Kroz koliko zemalja protiče reka Dunav: ",
    "odgovori_3" : ["6", "9", "10", "12"],
    "pitanje_4" : "Koja zemlja od ponudjenih ima najmanji broj stanovnika: ",
    "odgovori_4" : ["Indonezija", "Pakistan", "Nigerija", "Japan"],
    "pitanje_5" : "Koja od sledećih zemalja se ne graniči sa Srbijom: ",
    "odgovori_5" : ["Rumunija", "Slovačka", "Madjarska", "Bugarska"],
    "pitanje_6" : "Koja zemlja se graniči sa najviše drugih zemalja: ",
    "odgovori_6" : ["Kina", "Rusija", "SAD", "Brazil"],
    "pitanje_7" : "Koja od ponudjenih zemalja je 'najmladja' : ",
    "odgovori_7" : ["Senegal", "Singapur", "Libija", "Katar"],
    "pitanje_8" : "Koja je najveća zemlja(po površini), koja ne izlazi na more: ",
    "pitanje_9" : "U kom gradu se nalazi Crveni trg: ",
    "pitanje_10" : "Kroz koliko zemalja prolazi ekvator: "
}